webserver/__init__.py
webserver/__version__.py
webserver/conf.py
webserver/genconf.py
webserver/gendh.py
webserver/gentls.py
webserver/run.py
webserver/static.py
webserver/update.py
webserver/utils.py
webserver/config/443-template.conf
webserver/config/80-server.conf
webserver/config/integrated.yml
webserver/config/nginx.conf
webserver/config/defaults/php-proxy
webserver/config/defaults/proxy
webserver/config/defaults/ssl
webserver/config/examples/backend
webserver/config/examples/react
webserver/config/examples/wordpress
webserver-0.10.3.data/data/LICENSE
webserver-0.10.3.dist-info/LICENSE
webserver-0.10.3.dist-info/METADATA
webserver-0.10.3.dist-info/WHEEL
webserver-0.10.3.dist-info/entry_points.txt
webserver-0.10.3.dist-info/top_level.txt
webserver-0.10.3.dist-info/RECORD
