Metadata-Version: 2.1
Name: webserver
Version: 0.10.3
Summary: Simple to use CLI for setting up nginx webserver in Docker Swarm and adding websites' configs, proxies and static files
Home-page: https://gitlab.com/harry.sky.vortex/docker-webserver
Author: Igor Nehoroshev
Author-email: mail@neigor.me
License: Unlicense
Platform: UNKNOWN
Classifier: Development Status :: 3 - Alpha
Classifier: Environment :: Web Environment
Classifier: Intended Audience :: Developers
Classifier: License :: Public Domain
Classifier: Operating System :: OS Independent
Classifier: Programming Language :: Python :: 3
Classifier: Programming Language :: Python :: 3.7
Classifier: Programming Language :: Python :: 3.8
Requires-Python: >=3.7
Requires-Dist: click
Provides-Extra: lint
Requires-Dist: mypy ; extra == 'lint'
Requires-Dist: autoflake ; extra == 'lint'
Requires-Dist: black ; extra == 'lint'
Requires-Dist: isort ; extra == 'lint'
Provides-Extra: test
Requires-Dist: asynctest ; extra == 'test'
